[{"title": "Top 10 American Children Sentenced To Death", "hash": "a20ae9c3-9bc5-4a11-bc2a-7e02f8841e28", "cat": "Our World"}, {"title": "Top 10 Microscopic Monsters Lurking In Lakes", "hash": "359fcc25-0405-4a01-86e8-0a1e1ffd77b0", "cat": "Our World"}, {"title": "Top 10 Ghost Towns Inside Or Near Famous Cities", "hash": "e110d5dc-4e0b-463c-bae8-0e71d7f7dfa3", "cat": "Our World"}, {"title": "10 Of The Shortest-Lived Countries", "hash": "17279f10-3e9c-467c-954c-373d629c41b3", "cat": "Our World"}, {"title": "10 Lighthouses Built In Perfect Isolation", "hash": "12e27c4b-53d6-436b-b542-c8f56d806aa9", "cat": "Our World"}, {"title": "Top 10 Rare Finds That Raised The Cool Factor In Science", "hash": "fe1e87e9-fbcf-49a7-aa31-ddffb0efc6b7", "cat": "Our World"}, {"title": "10 Deserted Towns That You\u2019ll Want To Visit", "hash": "83aad350-1587-4e50-b9e9-c10f7cc806f5", "cat": "Our World"}, {"title": "10 Fascinating Glimpses Into Ancient Daily Life", "hash": "3f8540af-864e-4f73-a8ec-dfc8418b4d4a", "cat": "Our World"}, {"title": "10 More Controversies Of The Future", "hash": "0a8be968-ed22-47e4-88ad-6262c2c91200", "cat": "Our World"}, {"title": "Top 10 Prehistoric Planetary Apocalypses", "hash": "75c8cdc6-f8ad-447e-89bc-2055e52cbf44", "cat": "Our World"}]