[{"title": "10 Ways Rising Sea Levels Are Hurting The World", "hash": "78db2348-4684-4eda-a5d7-c0c66aebfc10", "cat": "Our World"}, {"title": "10 Amazing Ancient Versions Of Household Items", "hash": "91273f6e-2491-49b3-a830-3b1898d69b99", "cat": "Our World"}, {"title": "10 Things That Developed Because Of The Great Depression", "hash": "056e900c-9c7d-4055-ab0d-c0ac7bc60e63", "cat": "Our World"}, {"title": "Top 10 Natural Disasters And Their Historical Consequences", "hash": "e10c07b5-7326-4c3d-b096-0d885188d291", "cat": "Our World"}, {"title": "10 Incredible Geological Oddities You Probably Haven\u2019t Heard Of", "hash": "a7b213de-9db8-434d-b892-138fbe12e18b", "cat": "Our World"}, {"title": "10 Misconceptions About Modern Earth", "hash": "cd91d480-0820-48c9-a9f2-afd1734f00b8", "cat": "Our World"}, {"title": "10 Startling Discoveries About Plants And Their Habits", "hash": "05b2dca9-71a8-4575-b5d2-589c4c5941aa", "cat": "Our World"}, {"title": "10 Reasons We Know Nothing", "hash": "ed3738da-bebf-4ad4-adee-ccf94f52a2d1", "cat": "Our World"}, {"title": "10 Science Fiction Doomsdays That Could Theoretically Happen", "hash": "052ccf04-4a98-442e-9cc6-4acf88a9299c", "cat": "Our World"}, {"title": "Top 10 Butterfly Effects That Completely Changed The World", "hash": "b157a9a2-179a-4a01-899c-825eaa99e689", "cat": "Our World"}]