[{"title": "Top 10 New Mysteries And Insights From Unusual Ancient Skeletons", "hash": "5b738d89-8771-448b-8156-2b805038ba8c", "cat": "Our World"}, {"title": "10 Unusual Finds That Challenged Scientific Beliefs", "hash": "fb8f2512-0237-4e74-8f45-2ab8367b0b4c", "cat": "Our World"}, {"title": "Top 10 Exceptionally Strange Fossils From Extinct Species", "hash": "26a18eea-a515-44bb-ad15-47c3a5c3a1ff", "cat": "Our World"}, {"title": "10 Famous Festivals That Ended In Complete Disaster", "hash": "45c134e3-617a-4d2e-97c0-c6b3f7a3c880", "cat": "Our World"}, {"title": "10 Legendary Treasures Still Waiting To Be Found", "hash": "c9c1fc10-435e-416c-b859-4bfcbad6471b", "cat": "Our World"}, {"title": "10 Types Of Bacteria With Real Superpowers", "hash": "32d709b1-f41d-438c-bfda-8dc1abc366f4", "cat": "Our World"}, {"title": "Top 10 Recent Finds Made By Archaeologists On Islands", "hash": "6c16264e-2594-4d5f-bd57-7e16165c7985", "cat": "Our World"}, {"title": "10 Horrifying Accounts Of North Korea\u2019s Prison Camps", "hash": "73aadb84-8314-44c8-8ac8-e5b15a2c0f0b", "cat": "Our World"}, {"title": "10 Amazing Secrets Recently Revealed At Historical Landmarks", "hash": "b834b1bc-5cd0-4268-b21b-d9d0bd304dc9", "cat": "Our World"}, {"title": "10 Ruins That Unexpectedly Delivered Exciting Discoveries", "hash": "602e8c78-e5dc-46b0-9840-0283e13dc4cd", "cat": "Our World"}]