[{"title": "10 Parts In The History Of Kinky Sex", "hash": "9c3c85d0-767c-4e35-916d-67004f75c38c", "cat": "Weird Stuff"}, {"title": "10 UFO Sightings From Very Early History", "hash": "93de08fa-1b24-40a4-8f6f-0763866c8749", "cat": "Weird Stuff"}, {"title": "10 Conspiracies And Crazy Claims From The Pine Gap Facility", "hash": "6540cb84-079d-4f58-8cbb-5659bcb7ac3e", "cat": "Weird Stuff"}, {"title": "Top 10 Castles And Bridges Supposedly Built By The Devil", "hash": "41512181-4fdb-4d16-854d-385ac0ff73b6", "cat": "Weird Stuff"}, {"title": "10 Alleged UFO Sightings Witnessed By Students At School", "hash": "a4104cff-d0ec-4504-8eb2-cf57c006dc20", "cat": "Weird Stuff"}, {"title": "10 Bizarre Things You Didn\u2019t Know About Christmas", "hash": "d687719c-7097-4b6e-b0e7-8d48a043eab0", "cat": "Weird Stuff"}, {"title": "Top 10 Strangest Wikipedia Edit Wars", "hash": "dab5cd50-5edd-4621-b4b5-b41eb28122c0", "cat": "Weird Stuff"}, {"title": "10 Forbidden And Creepy Claims Of Giant Human Skeletons", "hash": "af65c086-a1e0-4c0e-90fa-391feedc2c49", "cat": "Weird Stuff"}, {"title": "10 Alleged Secret Weapons Of The US Military", "hash": "18f92b2c-df3f-4791-b66c-378631decac6", "cat": "Weird Stuff"}, {"title": "10 Global Versions Of The Lady In White Legend", "hash": "5fa94f7f-94b9-49be-9623-867eccd28914", "cat": "Weird Stuff"}]