[{"title": "10 Intriguing Mysteries About Sound-Related Phenomena", "hash": "22a90a02-1c1b-4e6c-beb1-6b306ace8fbe", "cat": "Mysteries"}, {"title": "10 Myths And Mysteries From The Cult Of Mithras", "hash": "a0a5ced4-012e-4f78-a801-4573b029f896", "cat": "Mysteries"}, {"title": "10 Historic Paintings That Clearly Show UFOs", "hash": "04db4286-c80b-4016-a756-a0e5fc8879c2", "cat": "Mysteries"}, {"title": "10 Mysterious Cats Of Great Britain", "hash": "22c8e1c1-3940-49c9-b779-9aeb68f0e447", "cat": "Mysteries"}, {"title": "10 Victims Who Went Unidentified for Years", "hash": "802da795-1c98-448d-91c8-d9d9f4d0c531", "cat": "Mysteries"}, {"title": "10 Mysterious Discoveries Of Human Body Parts", "hash": "68904b19-1bb8-4e7f-8488-5ade9768e49f", "cat": "Mysteries"}, {"title": "10 Mysteries Of Nature That Are Finally Solved", "hash": "8ee1bb88-57a7-4a00-acec-42194226cfff", "cat": "Mysteries"}, {"title": "10 Creepy Unsolved Mysteries From Australia", "hash": "9d33dff8-b40c-40a1-9392-5250b46a1232", "cat": "Mysteries"}, {"title": "10 Unsolved Cases That Involved Mysterious Phone Calls", "hash": "b4d7fcf4-e938-4597-8f5a-1099f6ce6f77", "cat": "Mysteries"}, {"title": "10 Creepy Mysteries Involving Abandoned Vehicles", "hash": "82ca70d7-d9f8-4210-bb2d-7d7f2110053d", "cat": "Mysteries"}]