[{"title": "10 Dangerous Animals That Escaped Captivity", "hash": "0e36c48b-87d3-434e-8dc8-9c01bab4ec2e", "cat": "Animals"}, {"title": "10 Strangest Defense Mechanisms In Nature", "hash": "e41b1bba-9eff-4f87-87cb-d2883787d5f1", "cat": "Animals"}, {"title": "10 Recently Extinct\u00a0Animals", "hash": "3a8a9807-ff82-4be9-b3ca-0d9feac46ecf", "cat": "Animals"}, {"title": "Top 10 Secret Ways Animals Help Humans", "hash": "2db04217-ca42-41b2-8421-17820e3aa9f9", "cat": "Animals"}, {"title": "10 Experiments That Have Created Real Human-Animal Hybrids", "hash": "d0eaf6ea-c5b3-4f2d-99dd-3970465cc9d3", "cat": "Animals"}, {"title": "10 Spineless Creatures That Could Decimate You", "hash": "9d0d75a6-4e18-423e-9097-fad22b1c5d5b", "cat": "Animals"}, {"title": "10 Species That Are Evolving Right Now", "hash": "51edfa15-e015-473b-a441-dda250832c3e", "cat": "Animals"}, {"title": "10 Insects That Belong in an Alien World", "hash": "2d598e1d-9727-46f2-be41-3c0964c8d71a", "cat": "Animals"}, {"title": "10 Fascinating Facts About Ferrets", "hash": "ecdc20ac-6432-4afa-bc3f-040d2e400477", "cat": "Animals"}, {"title": "10 Horrifying Facts About Ducks", "hash": "aa87479e-72db-4070-8ed5-080c48fdc9ce", "cat": "Animals"}]