[{"title": "10 Amazing Ways Tree-Dwelling Animals Fool Predators", "hash": "8ffa7863-f96a-47ae-842e-638014ef4d2e", "cat": "Animals"}, {"title": "10 Species That Are Surprisingly Ancient", "hash": "fa9dbe25-42fb-4216-8263-84404d856559", "cat": "Animals"}, {"title": "10 Incredible Stories Of Whales, Dolphins And Porpoises", "hash": "4d597f8e-13e4-4713-bc7d-9ccd86620d35", "cat": "Animals"}, {"title": "10 Mind-Bending Facts About Sea Stars", "hash": "fd618651-14b4-4ba3-a91c-be0bbcf2f744", "cat": "Animals"}, {"title": "10 Strange Features Recently Discovered In Prehistoric Creatures", "hash": "3e86009f-e5ca-4168-9794-8053c0b9103c", "cat": "Animals"}, {"title": "10 Bizarre Secondary Uses For Animal Body Parts", "hash": "d43ba689-eb33-45c5-967a-10c71d766740", "cat": "Animals"}, {"title": "10 Creepy Spiders We\u2019ve Recently Discovered", "hash": "2b913aab-9d0a-4925-a6bc-7cb08678cae6", "cat": "Animals"}, {"title": "10 Pairs Of Animals You Won\u2019t Believe Are Related", "hash": "87836dc3-21d6-4a3d-8d60-9519e43af8c7", "cat": "Animals"}, {"title": "10 Facts That Make Ferocious Animals Even More Terrifying", "hash": "857f7afa-ee67-448b-99c9-d614a93b0071", "cat": "Animals"}, {"title": "10 Of The Weirdest Experiments Ever Done With Animal Embryos", "hash": "41432369-9544-4931-a79f-0c4dfec9fa96", "cat": "Animals"}]