[{"title": "10 Reasons Academic Journals Are Filled With Junk Science", "hash": "790a4112-4b75-442e-972e-87649d828526", "cat": "Facts"}, {"title": "10 Inventions That Earned Their Creators Nothing", "hash": "e4ae3522-eb20-4a47-9313-e09df4c95b6e", "cat": "Facts"}, {"title": "10 Disgusting Facts About The Human Mouth", "hash": "382ea70f-730c-4a58-b7d6-04c3d9a8a7a7", "cat": "Facts"}, {"title": "10 Tragic Facts About Legendary Musicians", "hash": "4e1a3291-d1a5-45d9-9c1f-36d881d1fda5", "cat": "Facts"}, {"title": "10 Revolutionary Facts About The Bastille", "hash": "30a054bb-5f0c-4bd0-93fe-3f1732021c85", "cat": "Facts"}, {"title": "10 Fascinating Facts About The Human Skeleton", "hash": "7dbc1fcc-fbc7-4547-ba8c-fb2621268916", "cat": "Facts"}, {"title": "10 Intriguing Backstories Behind Common Symbols", "hash": "ac5f2edc-65fe-4767-a8e2-f0980ab50148", "cat": "Facts"}, {"title": "10 Horrifying Facts About Baby Farms", "hash": "e7776a09-fe5c-4555-8795-ecb391f924ad", "cat": "Facts"}, {"title": "Top 10 Intriguing Facts About Bitcoin", "hash": "63aa2fb2-54d9-4a73-b549-ad1035cafa28", "cat": "Facts"}, {"title": "10 Fascinating Theories To Explain D\u00e9j\u00e0 Vu", "hash": "926d50df-6a79-451c-ba1b-5250197ced8d", "cat": "Facts"}]