[{"title": "10 Ways Politicians Use Psychology To Manipulate Your Vote", "hash": "435bb65c-cfea-48aa-8b1d-771d3486eb56", "cat": "Politics"}, {"title": "10 Fascinating Fortune-Telling Techniques From History", "hash": "36315434-2460-4082-9207-556407025255", "cat": "History"}, {"title": "10 Examples Of Cloud Seeding And Weather Control", "hash": "d23aec81-f95f-4da0-ae01-59a0e161afc2", "cat": "Technology"}, {"title": "Top 10 US States That Did Not Make The Cut", "hash": "560d2eeb-ee05-46c8-b3c9-0292be24982c", "cat": "History"}, {"title": "10 Incredible Limbless Legends", "hash": "24e167dc-8c87-4970-9b4d-c6ab149340df", "cat": "Humans"}, {"title": "10 Insane Facts About Jennifer Lawrence\u2019s New Movie \u2018mother!\u2019", "hash": "57c2b047-0d13-466e-a169-c3a4df598289", "cat": "Movies and TV"}, {"title": "10 People Who Faked Their Own Suicides", "hash": "70ed0591-84a5-41ab-8795-8bedfbf1e027", "cat": "Crime"}, {"title": "10 Disturbing Aspects Of Stephen King\u2019s \u2018IT\u2019 Cut From The New Film", "hash": "7dc6a1bf-3e90-40d6-a38d-68f764eb5149", "cat": "Movies and TV"}, {"title": "10 Ways Pop Culture Has Skewed Our Perceptions About Psychopaths", "hash": "6c75224f-ed80-4bdc-9bdf-625128e5412b", "cat": "Pop Culture"}, {"title": "10 Epic Inventions Coming To Life At MIT", "hash": "f78f9592-85a9-4db2-bab9-35b935454d12", "cat": "Technology"}]