[{"title": "10 Hidden Images Discovered Beneath Famous Classic Paintings", "hash": "a7bf3766-d6d0-45da-ae4a-2a3d48ae6fb9", "cat": "The Arts"}, {"title": "10 Historical Challenges With Big Prizes That Spurred Great Innovations", "hash": "0dde0902-2fff-4606-8e84-fe6101734944", "cat": "History"}, {"title": "10 Haunting Murder Cases With Unsettling Selfies", "hash": "d3b4d010-13f8-469d-9634-dba33dab645e", "cat": "Crime"}, {"title": "10 Lesser-Known Transport Disasters Of The 20th Century", "hash": "fbe16985-b453-4267-baaa-6186937489eb", "cat": "Travel"}, {"title": "10 New World Explorers Overshadowed By Their More Famous Siblings", "hash": "967f1a98-f5fd-48a3-a80d-e853c0741346", "cat": "History"}, {"title": "10 Ways Video Games Affect Your Brain", "hash": "e615b236-a81a-4581-8214-7a0121b0bcde", "cat": "Gaming"}, {"title": "10 People Who Conducted Devastating Deceptions", "hash": "0ff232d2-9cd4-4bb9-90ae-2a92e35d16ab", "cat": "Crime"}, {"title": "10 Important Prehistoric Individuals Worth Knowing", "hash": "13ca17c6-020d-4220-b1d6-44960973513d", "cat": "History"}, {"title": "10 Of History\u2019s Most Terrifying And Brutal Pirates", "hash": "7a8d964c-f0cd-4417-9114-d5f91b2d1422", "cat": "History"}, {"title": "10 Totally Weird Vehicles From The 20th Century", "hash": "4bc7d353-b09c-405a-9a8c-e8a106ece02f", "cat": "Technology"}]