[{"title": "10 Crimes And Criminals Of Old China", "hash": "ef68ca36-8d2d-437d-9729-15d2cdef8e13", "cat": "Crime"}, {"title": "10 Fascinating Experimental Aircraft Of World War II", "hash": "ff88a556-6df6-442f-b7c2-5174417cb8f4", "cat": "Technology"}, {"title": "10 Important Things You Won\u2019t Believe We Managed To Lose Forever", "hash": "00713f02-134c-40d2-b734-3a6b9420c488", "cat": "Humans"}, {"title": "10 Unsolved Mysteries Involving Disturbing Phone Messages", "hash": "77f72c42-77d5-4631-aea5-59d42d72d8fe", "cat": "Mysteries"}, {"title": "10 Amazing Galactic Oddities", "hash": "11e84cc5-b59b-4dad-9c35-4a9f2cf1b934", "cat": "Space"}, {"title": "10 Pieces Of Celebrity Gold Hiding On YouTube", "hash": "1f1a654e-da03-453a-8025-764d5cc7ebbd", "cat": "Pop Culture"}, {"title": "10 Things You Didn\u2019t Know Babies Could Do", "hash": "0152a4e3-e414-45ea-bd16-d856a35579c6", "cat": "Facts"}, {"title": "10 Incredible Real-Life Stories Of Redemption", "hash": "b13046e9-7143-4128-9d11-0d875dff8a24", "cat": "Humans"}, {"title": "10 Wrongful Convictions Based On False Confessions", "hash": "db992aa1-0ec1-414d-8f43-86d9db900087", "cat": "Crime"}, {"title": "10 Common Things People Believed Were Invented By The Devil", "hash": "8b2eeab5-93b8-4b69-9667-42c512a61bcd", "cat": "Facts"}]