[{"title": "10 Mysteries Of Time", "hash": "91692858-71cf-45d2-bea9-1528ea95eb1a", "cat": "Our World"}, {"title": "10 Truly Strange Ways To Read Your Fortune", "hash": "2cf518e4-eadb-4ef0-b711-e3bd98a4d710", "cat": "Weird Stuff"}, {"title": "10 Ways That Light Pollution Harms The World", "hash": "17cc48ba-2f37-453d-8780-279ebb1fa913", "cat": "Our World"}, {"title": "10 Lighthouses Surrounded By Spooky Legends", "hash": "7387632c-d31f-4ac4-ac83-f357d747cf93", "cat": "Creepy"}, {"title": "10 Theories And Ideas That Hurt The World", "hash": "563c21e5-1560-4b37-9c15-46842da6c08c", "cat": "Our World"}, {"title": "10 Wildly Eccentric Characters From Victorian England", "hash": "c4c49194-f649-4100-be8b-7b3a48d320e5", "cat": "Humans"}, {"title": "10 Amazing Extremes Of Our Solar System", "hash": "4dde43f5-36b2-4efc-8675-3c1dc91057e2", "cat": "Space"}, {"title": "10 Old-Timers Who Kicked Ass During Wartime", "hash": "152b7740-5eb9-4b71-b131-014f77cb270f", "cat": "History"}, {"title": "10 Men Who Ate Anything And Everything", "hash": "29052f89-6615-4eef-a3ff-5f50f91a08ae", "cat": "Food"}, {"title": "10 Bizarre Firearms From History", "hash": "972e4e6b-ebbd-4b71-8f32-b43e1eb62f0c", "cat": "History"}]