[{"title": "10 Infuriating Cases Of Affluenza", "hash": "22b3a43d-8aae-465c-bed2-382036edc478", "cat": "Crime"}, {"title": "10 Common Misconceptions About Famous World Leaders", "hash": "0d10c6c8-90aa-4ed1-a59b-b25b76599f8b", "cat": "Misconceptions"}, {"title": "10 Archaeological Remains That Reveal Life In Ancient Babylon", "hash": "1be64e34-b976-453d-82f4-0a7602780bd9", "cat": "History"}, {"title": "10 Animals That Practice Homosexuality", "hash": "23696d5b-3fc8-49cd-9a40-ca8eb672eccd", "cat": "Animals"}, {"title": "10 Disturbing Cases Of Mass Hysterical Contagion Like \u2018Bird Box\u2019", "hash": "4fbb1cb8-0e24-4256-97bc-dcc99240565f", "cat": "Creepy"}, {"title": "10 Unusual Wedding Traditions From Around The World", "hash": "89c46ba5-7473-4948-8cfb-9c8e00c80742", "cat": "Humans"}, {"title": "10 Twisted And Unbelievable Facts About The Happy Face Killer", "hash": "96e338b1-f3ce-470d-b61e-b5b5c4e7e34e", "cat": "Crime"}, {"title": "Top 10 Facts That Change How You See The Story Of The Mayflower", "hash": "158fc928-87f6-4e15-8f98-75f9a9867c97", "cat": "History"}, {"title": "10 Ways We Could Get Messages From Advanced Aliens", "hash": "d8634ced-c3b1-4816-834c-b11fa9c623fa", "cat": "Space"}, {"title": "10 Ways To Get Rid Of A Body (And How They\u2019d Really Work Out)", "hash": "f4d7026f-f7bd-496f-8f3d-2a345040f4b3", "cat": "Creepy"}]