[{"title": "10 Scandalous Queens Who Shaped History", "hash": "5ad51e6a-bbdf-4ee0-a880-5a9523ea6554", "cat": "History"}, {"title": "10 Positive Things The Soviet Union Did", "hash": "de89aeb4-12fe-4d7a-95a3-83bdfe8eaf93", "cat": "History"}, {"title": "10 Forgotten Incidents Of Racial Violence In US History", "hash": "be595828-370a-441b-a1e8-8fe99c179f98", "cat": "History"}, {"title": "10 Japanese Weapons Invented Too Late To Win World War II", "hash": "09b4205a-de00-4413-93c9-79bdc12fadbe", "cat": "History"}, {"title": "10 Bizarre Inventions From The Victorian Era", "hash": "0b479bfe-cba1-4cb6-950b-6a3b3410cf1b", "cat": "History"}, {"title": "10 Sordid Insights Into The Victorian Opium Age", "hash": "d542f540-691a-44ae-b241-06c8fc181844", "cat": "History"}, {"title": "10 Semi-Legendary Kingdoms Of Modern National Groups", "hash": "592e4c64-7dc4-4c24-954f-3437de058a97", "cat": "History"}, {"title": "10 Fascinating Last Letters Of Prominent Historical Figures", "hash": "e63a1421-0b9b-473e-b32e-793a62b90745", "cat": "History"}, {"title": "10 Strange Cold War Tales Left Out Of The History Books", "hash": "00a88bef-fd43-4c43-88d1-64181d8b512d", "cat": "History"}, {"title": "10 Horrifying Facts About American Eugenics", "hash": "3d1d81d0-9e4f-4e6a-9bb9-54536daf2928", "cat": "History"}]