[{"title": "10 Of The Deadliest Riots In History", "hash": "631724d1-a44c-4aa2-a8f1-3b4d57f0fbc7", "cat": "History"}, {"title": "10 Mind-Blowing Wars That Nearly Happened", "hash": "25b95c3e-b190-47d6-ae39-a6dd62f08fb6", "cat": "History"}, {"title": "10 Epic Russian Military Disasters", "hash": "725695c2-f2d6-4ed6-b0e6-ce351087c3d4", "cat": "History"}, {"title": "10 Of The Wildest Parties In History", "hash": "7d746538-96eb-41ba-995e-4ed77662d3e5", "cat": "History"}, {"title": "10 Ways History Worked Children To Death", "hash": "ef75bf16-c5d2-46a2-a1ac-ab31f016a25e", "cat": "History"}, {"title": "10 Mythological Origin Stories About Fruit", "hash": "ab75e787-5686-4be4-afd4-acde23bd1547", "cat": "History"}, {"title": "10 Of The Deadliest Sieges In History", "hash": "fac6dcde-8cf9-408c-951b-2f52b7924496", "cat": "History"}, {"title": "10 Lesser-Known Sex Scandals Involving Powerful Men", "hash": "092880ef-57c8-4f1d-98e3-53d4f417c0e8", "cat": "History"}, {"title": "10 Astonishing Desert Survival Tales", "hash": "78f51712-ccfd-4ee9-8591-6ff5aa72a100", "cat": "History"}, {"title": "10 Cruel And Unusual Facts About The Colosseum\u2019s Animal Fights", "hash": "075b3d99-44b6-45d1-bd64-c5b13dc58608", "cat": "History"}]